streamlit_slb_video_image_gallery/__init__.py
streamlit_slb_video_image_gallery/example.py
streamlit_slb_video_image_gallery/frontend/build/asset-manifest.json
streamlit_slb_video_image_gallery/frontend/build/favicon.ico
streamlit_slb_video_image_gallery/frontend/build/index.html
streamlit_slb_video_image_gallery/frontend/build/logo192.png
streamlit_slb_video_image_gallery/frontend/build/logo512.png
streamlit_slb_video_image_gallery/frontend/build/manifest.json
streamlit_slb_video_image_gallery/frontend/build/robots.txt
streamlit_slb_video_image_gallery/frontend/build/static/css/main.3ce919c7.css
streamlit_slb_video_image_gallery/frontend/build/static/js/206.6aa589ab.chunk.js
streamlit_slb_video_image_gallery/frontend/build/static/js/main.22b9b3f4.js
streamlit_slb_video_image_gallery/frontend/build/static/js/main.22b9b3f4.js.LICENSE.txt
streamlit_slb_video_image_gallery/models/__init__.py
streamlit_slb_video_image_gallery-1.11.0.dist-info/LICENSE
streamlit_slb_video_image_gallery-1.11.0.dist-info/METADATA
streamlit_slb_video_image_gallery-1.11.0.dist-info/WHEEL
streamlit_slb_video_image_gallery-1.11.0.dist-info/top_level.txt
streamlit_slb_video_image_gallery-1.11.0.dist-info/RECORD
