Metadata-Version: 2.1
Name: streamlit-slb-video-image-gallery
Version: 1.11.0
Summary: Streamlit component that allows user to display image and video gallery
Home-page: 
Author: Sharizan Redzuan
Author-email: sredzuan@slb.com
Requires-Python: >=3.11
License-File: LICENSE
Requires-Dist: streamlit>=1.38
Provides-Extra: devel
Requires-Dist: wheel; extra == "devel"
Requires-Dist: pytest==7.4.0; extra == "devel"
Requires-Dist: playwright==1.39.0; extra == "devel"
Requires-Dist: requests==2.31.0; extra == "devel"
Requires-Dist: pytest-playwright-snapshot==1.0; extra == "devel"
Requires-Dist: pytest-rerunfailures==12.0; extra == "devel"
